README.md
pyproject.toml
setup.py
layout_cnab/__init__.py
layout_cnab/common/__init__.py
layout_cnab/common/converter.py
layout_cnab/common/header_arquivo.py
layout_cnab/common/header_lote.py
layout_cnab/common/layout.py
layout_cnab/common/options.py
layout_cnab/common/registro_detalhe_a.py
layout_cnab/common/registro_detalhe_b.py
layout_cnab/common/registro_trailer_arquivo.py
layout_cnab/common/registro_trailer_lote.py
layout_cnab/errors/__init__.py
layout_cnab_240.egg-info/PKG-INFO
layout_cnab_240.egg-info/SOURCES.txt
layout_cnab_240.egg-info/dependency_links.txt
layout_cnab_240.egg-info/top_level.txt