Metadata-Version: 2.1
Name: layout-cnab-240
Version: 1.0
Summary: Utility class to build batch file
Author: AdanEinstein
Author-email: adaneinstein@gmail.com
